{"data":{"site":{"siteMetadata":{"title":"Bee starter","configs":{"countOfInitialPost":10}}},"allMarkdownRemark":{"edges":[{"node":{"excerpt":"Getting Started 😎 1. Create a Gatsby site. If you are not using  , following  Gatsby Getting Started 2. Start developing. 3. Add your content You can write… contents to blog in   directory. resume   …","fields":{"slug":"/development/quick_start/"},"frontmatter":{"date":"May 31, 2019","title":"Quick Start","category":"development"}}},{"node":{"excerpt":"Welcome, Gatsby! This starter is full-package for your new blog! 1. Support Three frontmatter title date category 2. Code highlighting With  Fira Code  font Support highlighting with  prism \n2-1. Use…","fields":{"slug":"/development/hello/"},"frontmatter":{"date":"February 06, 2019","title":"Welcome Bee starter","category":"development"}}},{"node":{"excerpt":"Second Post","fields":{"slug":"/development/second/"},"frontmatter":{"date":"February 03, 2019","title":"Second Post","category":"development"}}},{"node":{"excerpt":"Third Post","fields":{"slug":"/development/third/"},"frontmatter":{"date":"February 01, 2019","title":"Third Post","category":"development"}}}]}},"pageContext":{"isCreatedByStatefulCreatePages":true}}